{
  "article_name": "SubLim",
  "statements": [
    {
      "stmt_id": "st_intro_oscillation",
      "subtype": "remark",
      "clause_range": [
        2,
        5
      ],
      "truth_value": null,
      "scope_id": "root",
      "exposed_entities": []
    },
    {
      "stmt_id": "st_intro_figure",
      "subtype": "remark",
      "clause_range": [
        6,
        10
      ],
      "truth_value": null,
      "scope_id": "root",
      "exposed_entities": []
    },
    {
      "stmt_id": "st_intro_need_supinf",
      "subtype": "remark",
      "clause_range": [
        11,
        11
      ],
      "truth_value": null,
      "scope_id": "root",
      "exposed_entities": []
    },
    {
      "stmt_id": "st_def1_let",
      "subtype": "assumption",
      "clause_range": [
        13,
        13
      ],
      "truth_value": null,
      "scope_id": "s_def1_let",
      "exposed_entities": [
        "x_n",
        "l_n",
        "h_n"
      ]
    },
    {
      "stmt_id": "st_def1_explain_l_n",
      "subtype": "remark",
      "clause_range": [
        14,
        15
      ],
      "truth_value": null,
      "scope_id": "s_def1",
      "exposed_entities": []
    },
    {
      "stmt_id": "st_def1_cond_upper",
      "subtype": "assumption",
      "clause_range": [
        16,
        16
      ],
      "truth_value": null,
      "scope_id": "s_def1",
      "exposed_entities": []
    },
    {
      "stmt_id": "st_def1_def_upperlim",
      "subtype": "definition",
      "clause_range": [
        17,
        17
      ],
      "truth_value": null,
      "scope_id": "s_def1",
      "exposed_entities": [
        "h"
      ]
    },
    {
      "stmt_id": "st_def1_cond_lower",
      "subtype": "assumption",
      "clause_range": [
        18,
        18
      ],
      "truth_value": null,
      "scope_id": "s_def1",
      "exposed_entities": []
    },
    {
      "stmt_id": "st_def1_def_lowerlim",
      "subtype": "definition",
      "clause_range": [
        19,
        19
      ],
      "truth_value": null,
      "scope_id": "s_def1",
      "exposed_entities": [
        "l"
      ]
    },
    {
      "stmt_id": "st_def1_notation",
      "subtype": "remark",
      "clause_range": [
        20,
        21
      ],
      "truth_value": null,
      "scope_id": "s_def1",
      "exposed_entities": []
    },
    {
      "stmt_id": "st_def1_figure_comment",
      "subtype": "remark",
      "clause_range": [
        22,
        22
      ],
      "truth_value": null,
      "scope_id": "s_def1",
      "exposed_entities": []
    },
    {
      "stmt_id": "st_ex1_let",
      "subtype": "assumption",
      "clause_range": [
        24,
        24
      ],
      "truth_value": null,
      "scope_id": "s_ex1_let",
      "exposed_entities": [
        "x_n",
        "l",
        "h"
      ]
    },
    {
      "stmt_id": "st_ex1_conclusion",
      "subtype": "conclusion",
      "clause_range": [
        25,
        26
      ],
      "truth_value": "conditional",
      "scope_id": "s_ex1",
      "exposed_entities": []
    },
    {
      "stmt_id": "st_ex1_remark",
      "subtype": "remark",
      "clause_range": [
        27,
        27
      ],
      "truth_value": null,
      "scope_id": "s_ex1",
      "exposed_entities": []
    },
    {
      "stmt_id": "st_thm1_equiv",
      "subtype": "theorem",
      "clause_range": [
        29,
        33
      ],
      "truth_value": "true",
      "scope_id": "s_thm1",
      "exposed_entities": []
    },
    {
      "stmt_id": "st_thm1_remark_accumulation",
      "subtype": "remark",
      "clause_range": [
        35,
        40
      ],
      "truth_value": null,
      "scope_id": "s_thm1",
      "exposed_entities": []
    },
    {
      "stmt_id": "st_def2_let",
      "subtype": "assumption",
      "clause_range": [
        42,
        42
      ],
      "truth_value": null,
      "scope_id": "s_def2_let",
      "exposed_entities": [
        "E"
      ]
    },
    {
      "stmt_id": "st_def2_definition",
      "subtype": "definition",
      "clause_range": [
        43,
        44
      ],
      "truth_value": null,
      "scope_id": "s_def2",
      "exposed_entities": [
        "x_0"
      ]
    },
    {
      "stmt_id": "st_def2_remark",
      "subtype": "remark",
      "clause_range": [
        45,
        49
      ],
      "truth_value": null,
      "scope_id": "s_def2",
      "exposed_entities": []
    },
    {
      "stmt_id": "st_thm2_let",
      "subtype": "assumption",
      "clause_range": [
        51,
        51
      ],
      "truth_value": null,
      "scope_id": "s_thm2_let",
      "exposed_entities": [
        "x_n"
      ]
    },
    {
      "stmt_id": "st_thm2_max_min_accum",
      "subtype": "theorem",
      "clause_range": [
        52,
        52
      ],
      "truth_value": "true",
      "scope_id": "s_thm2",
      "exposed_entities": []
    },
    {
      "stmt_id": "st_thm2_subseq_ineq",
      "subtype": "theorem",
      "clause_range": [
        53,
        54
      ],
      "truth_value": "true",
      "scope_id": "s_thm2",
      "exposed_entities": []
    },
    {
      "stmt_id": "st_thm2_equiv_lim",
      "subtype": "theorem",
      "clause_range": [
        55,
        55
      ],
      "truth_value": "true",
      "scope_id": "s_thm2",
      "exposed_entities": []
    },
    {
      "stmt_id": "st_ex2_let",
      "subtype": "assumption",
      "clause_range": [
        57,
        57
      ],
      "truth_value": null,
      "scope_id": "s_ex2_let",
      "exposed_entities": [
        "E"
      ]
    },
    {
      "stmt_id": "st_ex2_prove_infinite",
      "subtype": "exercise",
      "clause_range": [
        58,
        58
      ],
      "truth_value": "unknown",
      "scope_id": "s_ex2",
      "exposed_entities": []
    },
    {
      "stmt_id": "st_ex2_prove_properties",
      "subtype": "exercise",
      "clause_range": [
        59,
        59
      ],
      "truth_value": "unknown",
      "scope_id": "s_ex2",
      "exposed_entities": []
    },
    {
      "stmt_id": "st_ex2_prove_sin_n",
      "subtype": "exercise",
      "clause_range": [
        60,
        60
      ],
      "truth_value": "unknown",
      "scope_id": "s_ex2",
      "exposed_entities": []
    },
    {
      "stmt_id": "st_ex2_question_sum_product",
      "subtype": "question",
      "clause_range": [
        61,
        62
      ],
      "truth_value": "unknown",
      "scope_id": "s_ex2",
      "exposed_entities": []
    },
    {
      "stmt_id": "st_ex2_question_nonneg",
      "subtype": "question",
      "clause_range": [
        63,
        63
      ],
      "truth_value": "unknown",
      "scope_id": "s_ex2",
      "exposed_entities": []
    },
    {
      "stmt_id": "st_def3_let",
      "subtype": "assumption",
      "clause_range": [
        65,
        65
      ],
      "truth_value": null,
      "scope_id": "s_def3_let",
      "exposed_entities": [
        "x_n"
      ]
    },
    {
      "stmt_id": "st_def3_definition",
      "subtype": "definition",
      "clause_range": [
        65,
        66
      ],
      "truth_value": null,
      "scope_id": "s_def3",
      "exposed_entities": []
    },
    {
      "stmt_id": "st_thm3_equiv",
      "subtype": "theorem",
      "clause_range": [
        68,
        68
      ],
      "truth_value": "true",
      "scope_id": "s_thm3",
      "exposed_entities": []
    },
    {
      "stmt_id": "st_thm4_let",
      "subtype": "assumption",
      "clause_range": [
        70,
        70
      ],
      "truth_value": null,
      "scope_id": "s_thm4_let",
      "exposed_entities": [
        "f",
        "q"
      ]
    },
    {
      "stmt_id": "st_thm4_conclusion",
      "subtype": "theorem",
      "clause_range": [
        71,
        71
      ],
      "truth_value": "true",
      "scope_id": "s_thm4",
      "exposed_entities": [
        "c"
      ]
    },
    {
      "stmt_id": "st_thm4_proof_sketch",
      "subtype": "remark",
      "clause_range": [
        72,
        72
      ],
      "truth_value": null,
      "scope_id": "s_thm4",
      "exposed_entities": []
    },
    {
      "stmt_id": "st_ex3_negation",
      "subtype": "exercise",
      "clause_range": [
        74,
        74
      ],
      "truth_value": "unknown",
      "scope_id": "s_ex3",
      "exposed_entities": []
    },
    {
      "stmt_id": "st_ex3_nested_intervals",
      "subtype": "exercise",
      "clause_range": [
        75,
        75
      ],
      "truth_value": "unknown",
      "scope_id": "s_ex3",
      "exposed_entities": []
    },
    {
      "stmt_id": "st_ex3_let",
      "subtype": "assumption",
      "clause_range": [
        76,
        76
      ],
      "truth_value": null,
      "scope_id": "s_ex3_let",
      "exposed_entities": [
        "p_n",
        "q_n"
      ]
    },
    {
      "stmt_id": "st_ex3_conclusion",
      "subtype": "exercise",
      "clause_range": [
        76,
        76
      ],
      "truth_value": "unknown",
      "scope_id": "s_ex3",
      "exposed_entities": []
    }
  ],
  "edges": [
    {
      "source": "st_def1_let",
      "target": "st_def1_def_upperlim",
      "edge_type": "implies",
      "category": "logic"
    },
    {
      "source": "st_def1_cond_upper",
      "target": "st_def1_def_upperlim",
      "edge_type": "implies",
      "category": "logic"
    },
    {
      "source": "st_def1_let",
      "target": "st_def1_def_lowerlim",
      "edge_type": "implies",
      "category": "logic"
    },
    {
      "source": "st_def1_cond_lower",
      "target": "st_def1_def_lowerlim",
      "edge_type": "implies",
      "category": "logic"
    },
    {
      "source": "st_ex1_let",
      "target": "st_ex1_conclusion",
      "edge_type": "implies",
      "category": "logic"
    },
    {
      "source": "st_def2_let",
      "target": "st_def2_definition",
      "edge_type": "implies",
      "category": "logic"
    },
    {
      "source": "st_thm2_let",
      "target": "st_thm2_max_min_accum",
      "edge_type": "implies",
      "category": "logic"
    },
    {
      "source": "st_thm2_let",
      "target": "st_thm2_subseq_ineq",
      "edge_type": "implies",
      "category": "logic"
    },
    {
      "source": "st_thm2_let",
      "target": "st_thm2_equiv_lim",
      "edge_type": "implies",
      "category": "logic"
    },
    {
      "source": "st_ex2_let",
      "target": "st_ex2_prove_infinite",
      "edge_type": "implies",
      "category": "logic"
    },
    {
      "source": "st_def3_let",
      "target": "st_def3_definition",
      "edge_type": "implies",
      "category": "logic"
    },
    {
      "source": "st_thm4_let",
      "target": "st_thm4_conclusion",
      "edge_type": "implies",
      "category": "logic"
    },
    {
      "source": "st_ex3_let",
      "target": "st_ex3_conclusion",
      "edge_type": "implies",
      "category": "logic"
    }
  ],
  "cross_scope_edges": [
    {
      "source": "st_thm2_max_min_accum",
      "target": "st_def2_definition",
      "edge_type": "special_case",
      "category": "logic",
      "note": "定理2涉及聚点概念，依赖于定义2"
    },
    {
      "source": "st_thm3_equiv",
      "target": "st_def3_definition",
      "edge_type": "special_case",
      "category": "logic",
      "note": "定理3涉及柯西序列概念，依赖于定义3"
    },
    {
      "source": "st_thm4_conclusion",
      "target": "st_thm3_equiv",
      "edge_type": "special_case",
      "category": "logic",
      "note": "压缩映像定理的证明使用柯西收敛准则"
    }
  ],
  "unresolved": []
}